venv/bin/activate_this.py
wildebeest/__init__.py
wildebeest/__main__.py
wildebeest/wb-analysis.pl
wildebeest/wb_analysis.py
wildebeest/wb_normalize.py
wildebeest/data/ArabicPresentationFormMappingAnnotated.tsv
wildebeest/data/CJKCompatibilityMappingAnnotated.tsv
wildebeest/data/CombiningModifierMappingAnnotated.tsv
wildebeest/data/CoreCompatibilityMappingAnnotated.tsv
wildebeest/data/DigitMappingAnnotated.tsv
wildebeest/data/EnclosureMappingAnnotated.tsv
wildebeest/data/EncodingRepairMappingAnnotated.tsv
wildebeest/data/FontSmallVerticalMappingAnnotated.tsv
wildebeest/data/PythonWildebeestMappingAnnotated.tsv
wildebeest/data/assert-preserve.tsv
wildebeest/data/assert.tsv
wildebeest/data/look-alikes.txt
wildebeest/old/normalize-old.py
wildebeest/test/__init__.py
wildebeest/test/sample_wb_analysis.py
wildebeest/test/test_wb_norm.py
wildebeest/test/data/corpus.txt
wildebeest/test/data/hello.txt
wildebeest/test/data/out.json.ref
wildebeest/test/data/out.txt.ref
wildebeest/test/data/phrasebook-deu-out.ref
wildebeest/test/data/phrasebook-dir-out.ref
wildebeest/test/data/wildebeest-test-analysis-pprint.txt
wildebeest/test/data/wildebeest-test-invalid-utf8.txt
wildebeest/test/data/wildebeest-test-norm-all.txt
wildebeest/test/data/wildebeest-test-norm-all.txt.ref
wildebeest/test/data/wildebeest-test-norm-custom.txt
wildebeest/test/data/wildebeest-test-norm-custom.txt.ref
wildebeest/test/data/wildebeest-test-norm.txt
wildebeest/test/data/wildebeest-test-norm.txt.ref
wildebeest/test/data/wildebeest-test-out.ref
wildebeest/test/data/wildebeest-test.txt
wildebeest/test/data/phrasebook/deu.txt
wildebeest/test/data/phrasebook/ell.txt
wildebeest/test/data/phrasebook/eng.txt
wildebeest_nlp-0.9.2.dist-info/LICENSE
wildebeest_nlp-0.9.2.dist-info/METADATA
wildebeest_nlp-0.9.2.dist-info/WHEEL
wildebeest_nlp-0.9.2.dist-info/entry_points.txt
wildebeest_nlp-0.9.2.dist-info/top_level.txt
wildebeest_nlp-0.9.2.dist-info/RECORD
