Metadata-Version: 2.1
Name: wildebeest-nlp
Version: 0.9.2
Summary: The wildebeest scripts investigate, repair and normalize a wide range of text file problems at the character level, e.g. encoding errors, normalization of characters into their canonical form, mapping digits and some punctuation to ASCII, deletion of some non-printable characters.
Home-page: https://github.com/uhermjakob/wildebeest
Download-URL: https://github.com/uhermjakob/wildebeest
Author: Ulf Hermjakob
Author-email: ulf@isi.edu
License: UNKNOWN
Keywords: machine translation,datasets,NLP,natural language processing,computational linguistics
Platform: any
Classifier: Development Status :: 5 - Production/Stable
Classifier: Intended Audience :: Developers
Classifier: Topic :: Utilities
Classifier: Topic :: Text Processing
Classifier: Topic :: Text Processing :: General
Classifier: Topic :: Text Processing :: Filters
Classifier: Topic :: Text Processing :: Linguistic
Classifier: License :: OSI Approved :: Apache Software License
Classifier: Programming Language :: Python :: 3 :: Only
Requires-Python: >=3.8
License-File: LICENSE
Requires-Dist: regex (>=2021.8.3)
Requires-Dist: tqdm (>=4.40)
Requires-Dist: unicodeblock (>=0.3.1)
Requires-Dist: wheel (>=0.38.4)
